dropbase/__init__.py
dropbase/database/__init__.py
dropbase/database/connect.py
dropbase/database/database.py
dropbase/database/schemas.py
dropbase/database/sources.py
dropbase/database/databases/mysql.py
dropbase/database/databases/postgres.py
dropbase/database/databases/snowflake.py
dropbase/database/databases/sqlite.py
dropbase/helpers/__init__.py
dropbase/helpers/config.py
dropbase/helpers/logger.py
dropbase/helpers/state_handler.py
dropbase/models/__init__.py
dropbase/models/models.py
dropbase/models/state.py
dropbase/worker/__init__.py
dropbase/worker/run_python.py
dropbase-0.6.4.dist-info/METADATA
dropbase-0.6.4.dist-info/WHEEL
dropbase-0.6.4.dist-info/licenses/LICENSE
dropbase-0.6.4.dist-info/RECORD
