Metadata-Version: 2.3
Name: dropbase
Version: 0.6.4
Summary: Dropbase
Project-URL: Homepage, https://github.com/dropbase/dropbase_package
Project-URL: Bug Tracker, https://github.com/dropbase/dropbase_package/issues
Author-email: Dropbase <support@dropbase.io>
License-File: LICENSE
Classifier: License :: OSI Approved :: MIT License
Classifier: Operating System :: OS Independent
Classifier: Programming Language :: Python :: 3
Requires-Python: >=3.11
Requires-Dist: psycopg2-binary==2.9.9
Requires-Dist: sqlalchemy==1.4.46
